oasis_rofl_client/__about__.py
oasis_rofl_client/__init__.py
oasis_rofl_client/_version.py
oasis_rofl_client/py.typed
oasis_rofl_client/rofl_client.py
oasis_rofl_client_py_rube-0.0.4.dist-info/METADATA
oasis_rofl_client_py_rube-0.0.4.dist-info/WHEEL
oasis_rofl_client_py_rube-0.0.4.dist-info/licenses/LICENSE
oasis_rofl_client_py_rube-0.0.4.dist-info/RECORD
