Metadata-Version: 2.4
Name: oasis-rofl-client-py-rube
Version: 0.0.4
Summary: Python client SDK for Oasis ROFL.
Project-URL: Homepage, https://github.com/rube-de/oasis-rofl-client-py
Project-URL: Bug Tracker, https://github.com/rube-de/oasis-rofl-client-py/issues
Author-email: rube-de <bernhard@oasisprotocol.org>
License: Apache-2.0
License-File: LICENSE
Keywords: client,oasis,rofl,sdk
Classifier: License :: OSI Approved :: Apache Software License
Classifier: Operating System :: OS Independent
Classifier: Programming Language :: Python :: 3
Classifier: Programming Language :: Python :: 3.9
Classifier: Programming Language :: Python :: 3.10
Classifier: Programming Language :: Python :: 3.11
Classifier: Programming Language :: Python :: 3.12
Classifier: Typing :: Typed
Requires-Python: >=3.9
Requires-Dist: httpx>=0.25.0
